demo/__init__.py
demo/orthodr.py
demo/orthodr_cpp.cpython-36m-darwin.so
demo/yyggtest.py
yyggtest/__init__.py
yyggtest/orthodr_cpp.cpython-36m-darwin.so
yyggtest/ttpkg.cpython-36m-darwin.so
yyggtest/yyggtest.py
yyggtest-1.0.20.dist-info/METADATA
yyggtest-1.0.20.dist-info/WHEEL
yyggtest-1.0.20.dist-info/top_level.txt
yyggtest-1.0.20.dist-info/RECORD
